vkbottle_types/__init__.py
vkbottle_types/base_model.py
vkbottle_types/categories.py
vkbottle_types/codegen/__init__.py
vkbottle_types/codegen/methods/__init__.py
vkbottle_types/codegen/methods/account.py
vkbottle_types/codegen/methods/ads.py
vkbottle_types/codegen/methods/adsweb.py
vkbottle_types/codegen/methods/app_widgets.py
vkbottle_types/codegen/methods/apps.py
vkbottle_types/codegen/methods/auth.py
vkbottle_types/codegen/methods/board.py
vkbottle_types/codegen/methods/database.py
vkbottle_types/codegen/methods/docs.py
vkbottle_types/codegen/methods/donut.py
vkbottle_types/codegen/methods/downloaded_games.py
vkbottle_types/codegen/methods/fave.py
vkbottle_types/codegen/methods/friends.py
vkbottle_types/codegen/methods/gifts.py
vkbottle_types/codegen/methods/groups.py
vkbottle_types/codegen/methods/lead_forms.py
vkbottle_types/codegen/methods/likes.py
vkbottle_types/codegen/methods/market.py
vkbottle_types/codegen/methods/messages.py
vkbottle_types/codegen/methods/newsfeed.py
vkbottle_types/codegen/methods/notes.py
vkbottle_types/codegen/methods/notifications.py
vkbottle_types/codegen/methods/orders.py
vkbottle_types/codegen/methods/pages.py
vkbottle_types/codegen/methods/photos.py
vkbottle_types/codegen/methods/podcasts.py
vkbottle_types/codegen/methods/polls.py
vkbottle_types/codegen/methods/pretty_cards.py
vkbottle_types/codegen/methods/search.py
vkbottle_types/codegen/methods/secure.py
vkbottle_types/codegen/methods/stats.py
vkbottle_types/codegen/methods/status.py
vkbottle_types/codegen/methods/storage.py
vkbottle_types/codegen/methods/store.py
vkbottle_types/codegen/methods/stories.py
vkbottle_types/codegen/methods/streaming.py
vkbottle_types/codegen/methods/users.py
vkbottle_types/codegen/methods/utils.py
vkbottle_types/codegen/methods/video.py
vkbottle_types/codegen/methods/wall.py
vkbottle_types/codegen/methods/widgets.py
vkbottle_types/codegen/objects.py
vkbottle_types/codegen/responses/__init__.py
vkbottle_types/codegen/responses/account.py
vkbottle_types_vkru-5.131.146.16.2.dist-info/METADATA
vkbottle_types_vkru-5.131.146.16.2.dist-info/WHEEL
vkbottle_types_vkru-5.131.146.16.2.dist-info/licenses/LICENSE
vkbottle_types_vkru-5.131.146.16.2.dist-info/RECORD
