Metadata-Version: 2.4
Name: vkbottle-types-vkru
Version: 5.131.146.16.2
Summary: Types for vkbottle
License: MIT
License-File: LICENSE
Author: timoniq
Maintainer: FeeeeK
Requires-Python: >=3.7.2,<4.0.0
Classifier: License :: OSI Approved :: MIT License
Classifier: Programming Language :: Python :: 3
Classifier: Programming Language :: Python :: 3.8
Classifier: Programming Language :: Python :: 3.9
Classifier: Programming Language :: Python :: 3.10
Classifier: Programming Language :: Python :: 3.11
Classifier: Programming Language :: Python :: 3.12
Classifier: Programming Language :: Python :: 3.13
Classifier: Programming Language :: Python :: 3.14
Requires-Dist: pydantic (>=1.10.6,<3)
Requires-Dist: vkbottle-vkru (==4.3.12.2)
